{"nodes": [{"id": "home_david_documents_aurora_music_lib_features_home_widgets_home_widgets_dart", "label": "home_widgets.dart", "file_type": "code", "source_file": "lib/features/home/widgets/home_widgets.dart", "source_location": null}, {"id": "home_tab_dart", "label": "home_tab.dart", "file_type": "code", "source_file": null, "source_location": null}, {"id": "library_tab_dart", "label": "library_tab.dart", "file_type": "code", "source_file": null, "source_location": null}, {"id": "for_you_section_dart", "label": "for_you_section.dart", "file_type": "code", "source_file": null, "source_location": null}, {"id": "recently_played_section_dart", "label": "recently_played_section.dart", "file_type": "code", "source_file": null, "source_location": null}, {"id": "recently_added_section_dart", "label": "recently_added_section.dart", "file_type": "code", "source_file": null, "source_location": null}, {"id": "most_played_section_dart", "label": "most_played_section.dart", "file_type": "code", "source_file": null, "source_location": null}, {"id": "suggested_artists_section_dart", "label": "suggested_artists_section.dart", "file_type": "code", "source_file": null, "source_location": null}, {"id": "music_stats_card_dart", "label": "music_stats_card.dart", "file_type": "code", "source_file": null, "source_location": null}, {"id": "listening_history_card_dart", "label": "listening_history_card.dart", "file_type": "code", "source_file": null, "source_location": null}], "edges": [{"source": "home_david_documents_aurora_music_lib_features_home_widgets_home_widgets_dart", "target": "home_tab_dart", "relation": "exports", "confidence": "EXTRACTED", "confidence_score": 1.0, "source_file": "lib/features/home/widgets/home_widgets.dart", "source_location": null, "weight": 1.0}, {"source": "home_david_documents_aurora_music_lib_features_home_widgets_home_widgets_dart", "target": "library_tab_dart", "relation": "exports", "confidence": "EXTRACTED", "confidence_score": 1.0, "source_file": "lib/features/home/widgets/home_widgets.dart", "source_location": null, "weight": 1.0}, {"source": "home_david_documents_aurora_music_lib_features_home_widgets_home_widgets_dart", "target": "for_you_section_dart", "relation": "exports", "confidence": "EXTRACTED", "confidence_score": 1.0, "source_file": "lib/features/home/widgets/home_widgets.dart", "source_location": null, "weight": 1.0}, {"source": "home_david_documents_aurora_music_lib_features_home_widgets_home_widgets_dart", "target": "recently_played_section_dart", "relation": "exports", "confidence": "EXTRACTED", "confidence_score": 1.0, "source_file": "lib/features/home/widgets/home_widgets.dart", "source_location": null, "weight": 1.0}, {"source": "home_david_documents_aurora_music_lib_features_home_widgets_home_widgets_dart", "target": "recently_added_section_dart", "relation": "exports", "confidence": "EXTRACTED", "confidence_score": 1.0, "source_file": "lib/features/home/widgets/home_widgets.dart", "source_location": null, "weight": 1.0}, {"source": "home_david_documents_aurora_music_lib_features_home_widgets_home_widgets_dart", "target": "most_played_section_dart", "relation": "exports", "confidence": "EXTRACTED", "confidence_score": 1.0, "source_file": "lib/features/home/widgets/home_widgets.dart", "source_location": null, "weight": 1.0}, {"source": "home_david_documents_aurora_music_lib_features_home_widgets_home_widgets_dart", "target": "suggested_artists_section_dart", "relation": "exports", "confidence": "EXTRACTED", "confidence_score": 1.0, "source_file": "lib/features/home/widgets/home_widgets.dart", "source_location": null, "weight": 1.0}, {"source": "home_david_documents_aurora_music_lib_features_home_widgets_home_widgets_dart", "target": "music_stats_card_dart", "relation": "exports", "confidence": "EXTRACTED", "confidence_score": 1.0, "source_file": "lib/features/home/widgets/home_widgets.dart", "source_location": null, "weight": 1.0}, {"source": "home_david_documents_aurora_music_lib_features_home_widgets_home_widgets_dart", "target": "listening_history_card_dart", "relation": "exports", "confidence": "EXTRACTED", "confidence_score": 1.0, "source_file": "lib/features/home/widgets/home_widgets.dart", "source_location": null, "weight": 1.0}]}